abmodel/__init__.py
abmodel/agent/__init__.py
abmodel/agent/disease.py
abmodel/agent/movement.py
abmodel/agent/neighbors.py
abmodel/analysis/__init__.py
abmodel/analysis/aggregation.py
abmodel/models/__init__.py
abmodel/models/base.py
abmodel/models/disease.py
abmodel/models/health_system.py
abmodel/models/mobility_restrictions.py
abmodel/models/population.py
abmodel/population/__init__.py
abmodel/population/initial_arrangement.py
abmodel/population/population.py
abmodel/utils/__init__.py
abmodel/utils/distributions.py
abmodel/utils/execution_modes.py
abmodel/utils/helpers/__init__.py
abmodel/utils/helpers/distributions.py
abmodel/utils/units.py
abmodel/utils/utilities.py
cdslib_agents-0.0.9.dist-info/LICENSE
cdslib_agents-0.0.9.dist-info/WHEEL
cdslib_agents-0.0.9.dist-info/METADATA
cdslib_agents-0.0.9.dist-info/RECORD
