Metadata-Version: 2.1
Name: cdslib-agents
Version: 0.0.9
Summary: Contagious diseases simulation using Agent-Based Models
Home-page: https://pypi.org/project/cdslib-agents/
License: GPL-3.0-only
Keywords: Complex Systems,Computation,Epidemiology,Nonlinear dynamics,Agent Based Models
Author: Camilo Hincapié Gutiérrez
Author-email: camilo.hincapie@udea.edu.co
Maintainer: Vladimir Emil Rueda Gómez
Maintainer-email: vladimir.rueda@udea.edu.co
Requires-Python: >3.9,<3.11
Classifier: Intended Audience :: Developers
Classifier: Intended Audience :: Education
Classifier: Intended Audience :: Healthcare Industry
Classifier: Intended Audience :: Science/Research
Classifier: License :: OSI Approved :: GNU General Public License v3 (GPLv3)
Classifier: Natural Language :: English
Classifier: Operating System :: OS Independent
Classifier: Programming Language :: Python :: 3
Classifier: Programming Language :: Python :: 3.10
Classifier: Topic :: Education
Classifier: Topic :: Scientific/Engineering :: Medical Science Apps.
Classifier: Topic :: Software Development
Classifier: Topic :: Software Development :: Libraries
Requires-Dist: bokeh (>=2.4.3,<3.0.0)
Requires-Dist: dask (>=2022.4.0,<2023.0.0)
Requires-Dist: munch (>=2.5.0,<3.0.0)
Requires-Dist: numpy (>=1.21,<2.0)
Requires-Dist: pandas (>=1.2.4,<2.0.0)
Requires-Dist: pydantic (>=1.8.2,<2.0.0)
Requires-Dist: scikit-learn (>=0.24.2,<0.25.0)
Requires-Dist: scipy (>=1.6.3,<2.0.0)
Requires-Dist: snakeviz (>=2.1.1,<3.0.0)
Project-URL: Documentation, https://fenfisdi.github.io/cdslib/agents.html
Project-URL: Repository, https://github.com/fenfisdi/cdslib_agents
